yu_terms_mcp_server/__init__.py
yu_terms_mcp_server/main.py
yu_terms_mcp_server-1.0.5.dist-info/licenses/LICENSE
yu_terms_mcp_server-1.0.5.dist-info/METADATA
yu_terms_mcp_server-1.0.5.dist-info/WHEEL
yu_terms_mcp_server-1.0.5.dist-info/entry_points.txt
yu_terms_mcp_server-1.0.5.dist-info/top_level.txt
yu_terms_mcp_server-1.0.5.dist-info/RECORD
