Metadata-Version: 2.4
Name: yu-terms-mcp-server
Version: 1.0.5
Summary: A Python MCP server for terms management functionality
Author-email: YuPi <your-email@example.com>
License: MIT
Project-URL: Homepage, https://github.com/yourusername/yu-terms-mcp-server
Project-URL: Repository, https://github.com/yourusername/yu-terms-mcp-server
Project-URL: Issues, https://github.com/yourusername/yu-terms-mcp-server/issues
Keywords: mcp,server,terms,management
Classifier: Development Status :: 4 - Beta
Classifier: Intended Audience :: Developers
Classifier: License :: OSI Approved :: MIT License
Classifier: Programming Language :: Python :: 3
Classifier: Programming Language :: Python :: 3.8
Classifier: Programming Language :: Python :: 3.9
Classifier: Programming Language :: Python :: 3.10
Classifier: Programming Language :: Python :: 3.11
Classifier: Programming Language :: Python :: 3.12
Classifier: Programming Language :: Python :: 3.13
Requires-Python: >=3.10
License-File: LICENSE
Requires-Dist: mcp>=1.0.0
Requires-Dist: pydantic>=2.0.0
Requires-Dist: asyncio-mqtt>=0.16.0
Requires-Dist: typing-extensions>=4.0.0
Provides-Extra: dev
Requires-Dist: pytest>=7.0.0; extra == "dev"
Requires-Dist: pytest-asyncio>=0.21.0; extra == "dev"
Requires-Dist: black>=23.0.0; extra == "dev"
Requires-Dist: isort>=5.12.0; extra == "dev"
Requires-Dist: mypy>=1.0.0; extra == "dev"
Requires-Dist: flake8>=6.0.0; extra == "dev"
Dynamic: license-file
